testailib/__init__.py
testailib/handler.py
testailib/main.py
testailib/utils.py
testailib/crews/__init__.py
testailib/crews/cypress/__init__.py
testailib/crews/cypress/crew.py
testailib/crews/cypress/dicts/__init__.py
testailib/crews/cypress/dicts/agents.py
testailib/crews/cypress/dicts/output_examples.py
testailib/crews/cypress/dicts/tasks.py
testailib/crews/gherkin/__init__.py
testailib/crews/gherkin/crew.py
testailib/crews/gherkin/dicts/__init__.py
testailib/crews/gherkin/dicts/agents.py
testailib/crews/gherkin/dicts/tasks.py
testailib/crews/unit/__init__.py
testailib/crews/unit/crew.py
testailib/crews/unit/dicts/__init__.py
testailib/crews/unit/dicts/agents.py
testailib/crews/unit/dicts/files.py
testailib/crews/unit/dicts/tasks.py
testailib/crews/xunit/__init__.py
testailib/crews/xunit/crew.py
testailib/crews/xunit/dicts/__init__.py
testailib/crews/xunit/dicts/agents.py
testailib/crews/xunit/dicts/output_examples.py
testailib/crews/xunit/dicts/tasks.py
test_ai_leds-0.1.7.5.dist-info/METADATA
test_ai_leds-0.1.7.5.dist-info/WHEEL
test_ai_leds-0.1.7.5.dist-info/entry_points.txt
test_ai_leds-0.1.7.5.dist-info/top_level.txt
test_ai_leds-0.1.7.5.dist-info/RECORD
