Metadata-Version: 2.4
Name: test_ai_leds
Version: 0.1.7.5
Summary: AI automated test generation
Author: LEDS
Author-email: gabrieldpbrunetti@gmail.com
Requires-Dist: crewai==0.86.0
Requires-Dist: crewai_tools==0.17.0
Requires-Dist: google_generativeai
Requires-Dist: pyaml
Requires-Dist: chardet
Dynamic: author
Dynamic: author-email
Dynamic: description
Dynamic: description-content-type
Dynamic: requires-dist
Dynamic: summary
